pandix/__init__.py
pandix-0.0.1.dist-info/LICENSE
pandix-0.0.1.dist-info/METADATA
pandix-0.0.1.dist-info/WHEEL
pandix-0.0.1.dist-info/top_level.txt
pandix-0.0.1.dist-info/RECORD
